{
  "id": "Q-A-3_flashback_arrestors_20000031",
  "taskId": "A-3",
  "difficulty": "medium",
  "stem": "What device helps prevent flame traveling back into кислородно‑топливных рукаваs?",
  "choices": [
    {
      "id": "CHOICE-1",
      "text": "A расходомера"
    },
    {
      "id": "CHOICE-2",
      "text": "A check valve or огнепреградителя/клапана обратного удара"
    },
    {
      "id": "CHOICE-3",
      "text": "A pressure gauge"
    },
    {
      "id": "CHOICE-4",
      "text": "A рукава reel"
    }
  ],
  "correctId": "CHOICE-2",
  "rationales": {
    "CHOICE-2": "Check valves/огнепреградителя/клапана обратного удараs reduce flashback risk."
  }
}
