{
  "id": "Q-A-5_hi_lo_measure_2000006a",
  "taskId": "A-5",
  "difficulty": "medium",
  "stem": "Internal misalignment (hi‑lo) can be checked with:",
  "choices": [
    {
      "id": "CHOICE-1",
      "text": "A paint marker"
    },
    {
      "id": "CHOICE-2",
      "text": "A hi‑lo gauge or calipers"
    },
    {
      "id": "CHOICE-3",
      "text": "A thermometer"
    },
    {
      "id": "CHOICE-4",
      "text": "A voltmeter"
    }
  ],
  "correctId": "CHOICE-2",
  "rationales": {
    "CHOICE-2": "Use appropriate gauges to measure internal misalignment."
  }
}
