{
  "id": "Q-D-14_tungsten_contamination_v6_09_400000fe",
  "taskId": "D-14",
  "difficulty": "medium",
  "stem": "If tungsten touches the molten pool, you should:",
  "choices": [
    {
      "id": "CHOICE-1",
      "text": "Continue welding"
    },
    {
      "id": "CHOICE-2",
      "text": "Break off/resharpen tungsten and clean the area"
    },
    {
      "id": "CHOICE-3",
      "text": "Increase current"
    },
    {
      "id": "CHOICE-4",
      "text": "Change to CO₂ shielding"
    }
  ],
  "correctId": "CHOICE-2",
  "rationales": {
    "CHOICE-2": "Contamination requires regrinding and cleaning."
  }
}
