{
  "id": "Q-D-13_nozzle_tip_clean_v10_07_400000bb",
  "taskId": "D-13",
  "difficulty": "easy",
  "stem": "Почему keep the сопла and токоподводящего наконечника clean?",
  "choices": [
    {
      "id": "CHOICE-1",
      "text": "Increase spatter"
    },
    {
      "id": "CHOICE-2",
      "text": "Maintain газ coverage and stable contact"
    },
    {
      "id": "CHOICE-3",
      "text": "Reduce deположение rate"
    },
    {
      "id": "CHOICE-4",
      "text": "Cool the проволока"
    }
  ],
  "correctId": "CHOICE-2",
  "rationales": {
    "CHOICE-2": "Spatter buildup disturbs защитного газа/electrical continuity."
  }
}
