{
  "id": "Q-D-13_nozzle_care_1000006b",
  "taskId": "D-13",
  "difficulty": "easy",
  "stem": "Почему keep the GMAW (MIG/MAG) сопло and токоподводящего наконечника clean?",
  "choices": [
    {
      "id": "CHOICE-1",
      "text": "To увеличивает spatter"
    },
    {
      "id": "CHOICE-2",
      "text": "To maintain gas coverage and stable electrical контактный"
    },
    {
      "id": "CHOICE-3",
      "text": "To уменьшить deposition rate"
    },
    {
      "id": "CHOICE-4",
      "text": "To cool the wire"
    }
  ],
  "correctId": "CHOICE-2",
  "rationales": {
    "CHOICE-2": "Spatter buildup disturbs shielding and electrical continuity."
  }
}
