{
  "id": "Q-D-14_gas_flow_high_10000075",
  "taskId": "D-14",
  "difficulty": "medium",
  "stem": "К чему может привести чрезмерный GTAW (TIG) shielding gas flow cause?",
  "choices": [
    {
      "id": "CHOICE-1",
      "text": "Improved laminar flow"
    },
    {
      "id": "CHOICE-2",
      "text": "Turbulence that draws in air and contamination"
    },
    {
      "id": "CHOICE-3",
      "text": "No effect on shielding"
    },
    {
      "id": "CHOICE-4",
      "text": "Higher проплавление"
    }
  ],
  "correctId": "CHOICE-2",
  "rationales": {
    "CHOICE-2": "Too much flow creates turbulence and aspiration of air into the shield."
  }
}
