{
  "id": "Q-A-4_datum_on_drawing_20000048",
  "taskId": "A-4",
  "difficulty": "medium",
  "stem": "When measuring from drawings, a good practice is to:",
  "choices": [
    {
      "id": "CHOICE-1",
      "text": "Use any convenient edge as a baseline"
    },
    {
      "id": "CHOICE-2",
      "text": "Measure from the designated datum(s) shown"
    },
    {
      "id": "CHOICE-3",
      "text": "Scale dimensions from a printout"
    },
    {
      "id": "CHOICE-4",
      "text": "Guess from photos"
    }
  ],
  "correctId": "CHOICE-2",
  "rationales": {
    "CHOICE-2": "Use the specified datums to control tolerance stack‑up."
  }
}
