{
  "id": "Q-B-7_temporary_attachments_v2_04_30000041",
  "taskId": "B-7",
  "difficulty": "medium",
  "stem": "For temporary стронгбеков (жёстких распорок) or tabs, a best practice is to:",
  "choices": [
    {
      "id": "CHOICE-1",
      "text": "Leave them on finished products"
    },
    {
      "id": "CHOICE-2",
      "text": "Удалить and finish per drawings/WPS after welding"
    },
    {
      "id": "CHOICE-3",
      "text": "Ignore drawing requirements"
    },
    {
      "id": "CHOICE-4",
      "text": "Paint over them if visible"
    }
  ],
  "correctId": "CHOICE-2",
  "rationales": {
    "CHOICE-2": "Temporary attachments should be removed and finished as specified."
  }
}
