{
  "id": "Q-D-15_flux_coverage_v1_06_40000105",
  "taskId": "D-15",
  "difficulty": "easy",
  "stem": "During SAW (под флюсом), the arc should be:",
  "choices": [
    {
      "id": "CHOICE-1",
      "text": "Fully covered by флюса"
    },
    {
      "id": "CHOICE-2",
      "text": "Barely covered by флюса"
    },
    {
      "id": "CHOICE-3",
      "text": "Exposed for visibility"
    },
    {
      "id": "CHOICE-4",
      "text": "Alternatingly exposed"
    }
  ],
  "correctId": "CHOICE-1",
  "rationales": {
    "CHOICE-1": "Full флюса coverage provides защитного газа and шлака formation."
  }
}
