{
  "id": "Q-D-12_e7018_current_10000055",
  "taskId": "D-12",
  "difficulty": "easy",
  "stem": "Which power source setting can E7018 typically run on?",
  "choices": [
    {
      "id": "CHOICE-1",
      "text": "DCEN only"
    },
    {
      "id": "CHOICE-2",
      "text": "DCEP or AC, per manufacturer"
    },
    {
      "id": "CHOICE-3",
      "text": "AC only"
    },
    {
      "id": "CHOICE-4",
      "text": "DCEP only, never AC"
    }
  ],
  "correctId": "CHOICE-2",
  "rationales": {
    "CHOICE-2": "E7018 is usually suitable for DCEP and often AC depending on brand/WPS."
  }
}
