{
  "id": "Q-D-12_e7024_character_v8_08_4000004e",
  "taskId": "D-12",
  "difficulty": "medium",
  "stem": "Какое утверждение describes E7024 электроды?",
  "choices": [
    {
      "id": "CHOICE-1",
      "text": "Cellulosic покрытие, deep проплавление"
    },
    {
      "id": "CHOICE-2",
      "text": "High-deположение iron-powder rutile, flat/horizontal"
    },
    {
      "id": "CHOICE-3",
      "text": "Basic низководородное for all положениеs"
    },
    {
      "id": "CHOICE-4",
      "text": "Stainless steel welding only"
    }
  ],
  "correctId": "CHOICE-2",
  "rationales": {
    "CHOICE-2": "E7024 is iron-powder rutile for high deположение in flat/horizontal."
  }
}
