{
  "id": "Q-C-8_guard_position_10000033",
  "taskId": "C-8",
  "difficulty": "easy",
  "stem": "How should a grinder guard be positioned?",
  "choices": [
    {
      "id": "CHOICE-1",
      "text": "Aim sparks toward coworkers"
    },
    {
      "id": "CHOICE-2",
      "text": "Place the guard between the wheel and the operator"
    },
    {
      "id": "CHOICE-3",
      "text": "Remove the guard for visibility"
    },
    {
      "id": "CHOICE-4",
      "text": "Open the guard for cooling"
    }
  ],
  "correctId": "CHOICE-2",
  "rationales": {
    "CHOICE-2": "The guard should block fragments and direct debris away from the user."
  }
}
