{
  "schema": "qweld.question.v1",
  "id": "A-5_preheat_verify_20000055",
  "version": "1.0.0",
  "policyVersion": "1.0",
  "locale": "ru",
  "blockId": "A",
  "taskId": "A-5",
  "difficulty": "easy",
  "stem": "Что такое a reliable way to verify предварительный подогрев temperature?",
  "choices": [
    {
      "id": "A",
      "text": "By hand feel"
    },
    {
      "id": "B",
      "text": "Using temperature-indicating crayons or a thermometer"
    },
    {
      "id": "C",
      "text": "Watching for color change only"
    },
    {
      "id": "D",
      "text": "Assuming room temperature is enough"
    }
  ],
  "correctId": "B",
  "rationales": {
    "B": "Use objective temperature indicators to confirm предварительный подогрев."
  }
}